README.rst
layerz.py
setup.py
layerz.egg-info/PKG-INFO
layerz.egg-info/SOURCES.txt
layerz.egg-info/dependency_links.txt
layerz.egg-info/requires.txt
layerz.egg-info/top_level.txt