Metadata-Version: 1.0
Name: layerz
Version: 0.5
Summary: Module to create layers of dependencies
Home-page: http://github.com/delfick/layerz
Author: Stephen Moore
Author-email: delfick755@gmail.com
License: MIT
Platform: UNKNOWN
